aramex_lib/__init__.py
aramex_lib/array_of_string.py
aramex_lib/datatypes.py
aramex_lib/location.py
aramex_lib/rates.py
aramex_lib/shipping.py
aramex_lib/tracking.py
carrier.aramex-2021.2.dist-info/WHEEL
carrier.aramex-2021.2.dist-info/METADATA
carrier.aramex-2021.2.dist-info/RECORD
